auto_website_visitor/__init__.py
auto_website_visitor/_version.py
auto_website_visitor/browser.py
auto_website_visitor/cli.py
auto_website_visitor/config.py
auto_website_visitor/core.py
auto_website_visitor/logger.py
auto_website_visitor/scheduler.py
auto_website_visitor/updater.py
auto_website_visitor/templates/config.json
auto_website_visitor/templates/config.yaml
auto_website_visitor-2025.1.7.dist-info/licenses/LICENSE
auto_website_visitor-2025.1.7.dist-info/METADATA
auto_website_visitor-2025.1.7.dist-info/WHEEL
auto_website_visitor-2025.1.7.dist-info/entry_points.txt
auto_website_visitor-2025.1.7.dist-info/top_level.txt
auto_website_visitor-2025.1.7.dist-info/RECORD
