Metadata-Version: 2.4
Name: auto-website-visitor
Version: 2025.1.7
Summary: Automated website visitor with scheduling and advanced browser automation
Author-email: nayandas69 <nayanchandradas@hotmail.com>
License: MIT
Project-URL: Homepage, https://github.com/nayandas69/auto-website-visitor
Project-URL: Repository, https://github.com/nayandas69/auto-website-visitor
Project-URL: Issues, https://github.com/nayandas69/auto-website-visitor/issues
Classifier: Development Status :: 5 - Production/Stable
Classifier: Intended Audience :: Developers
Classifier: License :: OSI Approved :: MIT License
Classifier: Operating System :: OS Independent
Classifier: Programming Language :: Python :: 3.10
Classifier: Programming Language :: Python :: 3.11
Classifier: Topic :: Internet :: WWW/HTTP :: Browsers
Classifier: Topic :: Software Development :: Testing
Classifier: Topic :: System :: Monitoring
Requires-Python: >=3.10
License-File: LICENSE
Requires-Dist: selenium>=4.15.0
Requires-Dist: webdriver-manager>=4.0.0
Requires-Dist: click>=8.0.0
Requires-Dist: pyyaml>=6.0
Requires-Dist: schedule>=1.2.0
Requires-Dist: croniter>=1.4.0
Requires-Dist: colorama>=0.4.6
Requires-Dist: requests>=2.31.0
Requires-Dist: psutil>=5.9.0
Requires-Dist: packaging>=23.0
Provides-Extra: dev
Requires-Dist: pytest>=7.0.0; extra == "dev"
Requires-Dist: pytest-cov>=4.0.0; extra == "dev"
Requires-Dist: black>=23.0.0; extra == "dev"
Requires-Dist: flake8>=6.0.0; extra == "dev"
Requires-Dist: mypy>=1.0.0; extra == "dev"
Dynamic: license-file
